[
  {
    "name": "Fake Presta Shop",
    "url": "http://37.27.17.198:8084/cs/",
    "timestamp": "2026-07-17T11:16:05.124133+00:00",
    "status": "ok",
    "http_status": 200,
    "response_time_s": 1.16,
    "xpath_found": true,
    "errors": []
  },
  {
    "name": "CV Portal",
    "url": "https://cv.tesena.com/",
    "timestamp": "2026-07-17T11:16:06.285306+00:00",
    "status": "ok",
    "http_status": 200,
    "response_time_s": 0.753,
    "xpath_found": true,
    "errors": []
  },
  {
    "name": "Test Design Helper",
    "url": "https://testdesign.tesena.com/",
    "timestamp": "2026-07-17T11:16:07.039618+00:00",
    "status": "ok",
    "http_status": 200,
    "response_time_s": 0.853,
    "xpath_found": true,
    "errors": []
  },
  {
    "name": "QE Compass",
    "url": "https://qecompass.tesena.com/",
    "timestamp": "2026-07-17T11:16:07.894240+00:00",
    "status": "ok",
    "http_status": 200,
    "response_time_s": 0.722,
    "xpath_found": true,
    "errors": []
  }
]